LICENSE
MANIFEST.in
README.rst
setup.py
django_fontawesome.egg-info/PKG-INFO
django_fontawesome.egg-info/SOURCES.txt
django_fontawesome.egg-info/dependency_links.txt
django_fontawesome.egg-info/pbr.json
django_fontawesome.egg-info/requires.txt
django_fontawesome.egg-info/top_level.txt
fontawesome/__init__.py
fontawesome/fields.py
fontawesome/forms.py
fontawesome/icons.yml
fontawesome/models.py
fontawesome/utils.py
fontawesome/widgets.py
fontawesome/locale/fr/LC_MESSAGES/django.mo
fontawesome/locale/fr/LC_MESSAGES/django.po
fontawesome/static/fontawesome/css/font-awesome.min.css
fontawesome/static/fontawesome/fonts/FontAwesome.otf
fontawesome/static/fontawesome/fonts/fontawesome-webfont.eot
fontawesome/static/fontawesome/fonts/fontawesome-webfont.svg
fontawesome/static/fontawesome/fonts/fontawesome-webfont.ttf
fontawesome/static/fontawesome/fonts/fontawesome-webfont.woff
fontawesome/static/fontawesome/fonts/fontawesome-webfont.woff2
fontawesome/static/fontawesome/js/django_fontawesome.js
fontawesome/static/fontawesome/select2/select2-bootstrap.css
fontawesome/static/fontawesome/select2/select2-spinner.gif
fontawesome/static/fontawesome/select2/select2.css
fontawesome/static/fontawesome/select2/select2.min.js
fontawesome/static/fontawesome/select2/select2.png
fontawesome/templatetags/__init__.py
fontawesome/templatetags/fontawesome.py