Metadata-Version: 1.1
Name: django-fontawesome
Version: 0.2.6
Summary: a django app that provides a couple of fontawesome/django related utilities.
Home-page: https://www.github.com/redouane/django-fontawesome
Author: Redouane Zait
Author-email: redouanezait@gmail.com
License: BSD License
Platform: UNKNOWN
Classifier: Environment :: Web Environment
Classifier: Framework :: Django
Classifier: Intended Audience :: Developers
Classifier: License :: OSI Approved :: BSD License
Classifier: Operating System :: OS Independent
Classifier: Programming Language :: Python
Classifier: Programming Language :: Python :: 2
Classifier: Programming Language :: Python :: 2.6
Classifier: Programming Language :: Python :: 2.7
Classifier: Topic :: Utilities
